{
    "serverlogChannelUpdate": {
        "title": "Protokoll-Kanal geändert",
        "description_set": "{executor} hat den {type} Protokoll-Kanal nach {channel} gesetzt",
        "description_category_disable": "{executor} hat den {type} Protokoll-Kanal deaktiviert",
        "description_unset": "{executor} hat den {type} Protokoll-Kanal nicht mehr festgelegt"
    },
    "serverlogOptionsUpdate": {
        "title": "Protokolloptionen aktualisiert",
        "description": "{executor} hat {option} auf {state} gesetzt",
        "pluralkitSupport": "PluralKit Unterstützung",
        "spoilers": "Spoiler",
        "buttons": "Schaltflächen",
        "formatType": "Format Type"
    },
    "serverlogLogUpdate": {
        "title": "Protokoll aktualisiert",
        "description": "{executor} hat das {type} Protokoll aktualisiert",
        "enabled": "Aktiviert",
        "logFormat": "Format",
        "logChannel": "Kanal",
        "colour": "Farbe",
        "ignoreBotExecutors": "Ignoriere Bot-Ausführende",
        "ignoreBotTargets": "Ignoriere Bot-Ziele",
        "activeIgnore": "Aktiv ignorieren"
    },
    "serverlogIgnoreUpdate": {
        "title": "Optionen zum Ignorieren aktualisiert",
        "description_set": "{executor} aktivert {type}",
        "description_unset": "{executor} deaktivert {type}",
        "description_added": "{executor} fügt {target} zu {type} hinzu",
        "description_removed": "{executor} entfernt {target} von {type}"
    },
    "languageUpdate": {
        "title": "Sprache geändert",
        "description": "{executor} hat die Sprache zu {language} geändert"
    },
    "reset": {
        "title": "Konfiguration zurückgesetzt",
        "description": "{executor} hat die Konfiguration für den Server zurückgesetzt"
    },
    "tagAdded": {
        "title": "Tag hinzugefügt",
        "description": "{executor} hat den Tag {tag} erstellt"
    },
    "tagUpdated": {
        "title": "Tag aktualisiert",
        "description": "{executor} hat den Tag {tag} aktualisiert"
    },
    "tagDeleted": {
        "title": "Tag gelöscht",
        "description": "{executor} hat den Tag {tag} gelöscht"
    },
    "tokenAdded": {
        "title": "Token generiert",
        "description": "{executor} hat einen Quark Berechtigungsschlüssel für {permissions} Berechtigungen für diesen Server erstellt",
        "unique_id": "Token ID",
        "revoke": "Widerrufe den Token"
    },
    "tokenRevoked": {
        "title": "Token erfolgreich widerrufen",
        "description": "{executor} hat den Quark Berechtigungsschlüssel mit der ID {token} widerrufen"
    },
    "guildSubscriptionUpdate": {
        "title_applied": "Server Upgraded",
        "title_removed": "Server Downgraded",
        "description_applied": "This server now has [type] features enabled! 🎉",
        "description_removed": "This server is now using Quark's free tier",
        "quark_pro": "Quark Pro",
        "quark_prolite": "Quark Pro Lite",
        "none": "none",
        "executor": "Given by",
        "teaser_pro": "Enjoy extended message logging (up to 4 weeks), fully customizable logs, the Pro bot, and more... 🚀"
    },
    "guildSubscriptionsUpdate": {
        "teaser_pro": "Enjoy extended message logging (up to 4 weeks), fully customizable logs, the Pro bot, and more... 🚀"
    }
}
